geocube/__init__.py
geocube/_show_versions.py
geocube/exceptions.py
geocube/logger.py
geocube/py.typed
geocube/rasterize.py
geocube/vector.py
geocube/vector_to_cube.py
geocube/api/__init__.py
geocube/api/core.py
geocube/cli/__init__.py
geocube/cli/geocube.py
geocube/cli/commands/__init__.py
geocube/cli/commands/make_geocube.py
geocube/geo_utils/__init__.py
geocube/geo_utils/geobox.py
geocube/xarray_extensions/__init__.py
geocube/xarray_extensions/vectorxarray.py
geocube-0.7.0.dist-info/AUTHORS.rst
geocube-0.7.0.dist-info/LICENSE
geocube-0.7.0.dist-info/METADATA
geocube-0.7.0.dist-info/WHEEL
geocube-0.7.0.dist-info/entry_points.txt
geocube-0.7.0.dist-info/top_level.txt
geocube-0.7.0.dist-info/RECORD
