Metadata-Version: 2.1
Name: geocube
Version: 0.7.0
Summary: Tool to convert geopandas vector data into rasterized xarray data.
Maintainer: geocube Contributors
License: BSD-3-Clause
Project-URL: homepage, https://corteva.github.io/geocube/
Project-URL: documentation, https://corteva.github.io/geocube/
Project-URL: repository, https://github.com/corteva/geocube
Project-URL: changelog, https://corteva.github.io/geocube/stable/history.html
Keywords: GDAL,rasterize,vector
Classifier: Development Status :: 4 - Beta
Classifier: Intended Audience :: Developers
Classifier: Natural Language :: English
Classifier: License :: OSI Approved :: BSD License
Classifier: Operating System :: OS Independent
Classifier: Topic :: Scientific/Engineering :: GIS
Classifier: Programming Language :: Python
Classifier: Programming Language :: Python :: 3.10
Classifier: Programming Language :: Python :: 3.11
Classifier: Programming Language :: Python :: 3.12
Classifier: Programming Language :: Python :: 3
Classifier: Topic :: Software Development :: Libraries :: Python Modules
Classifier: Typing :: Typed
Requires-Python: >=3.10
License-File: LICENSE
License-File: AUTHORS.rst
Requires-Dist: appdirs
Requires-Dist: click>=6.0
Requires-Dist: geopandas>=1
Requires-Dist: odc-geo
Requires-Dist: rasterio>=1.3
Requires-Dist: rioxarray>=0.4
Requires-Dist: scipy
Requires-Dist: xarray>=0.17
Requires-Dist: pyproj>=2
Requires-Dist: numpy>=1.20
